{"root_path": "/home/sourove/Code/Python/torch/deepspeech2-Jupyter/data/train", "samples": [{"wav_path": "train_33/wav/00036554b6a1.wav", "transcript_path": "train_33/txt/00036554b6a1.txt"}, {"wav_path": "train_33/wav/0017dab04e35.wav", "transcript_path": "train_33/txt/0017dab04e35.txt"}, {"wav_path": "train_33/wav/0018d199c78c.wav", "transcript_path": "train_33/txt/0018d199c78c.txt"}, {"wav_path": "train_33/wav/0019f6076d6f.wav", "transcript_path": "train_33/txt/0019f6076d6f.txt"}, {"wav_path": "train_33/wav/002bdd43bf94.wav", "transcript_path": "train_33/txt/002bdd43bf94.txt"}, {"wav_path": "train_33/wav/004c58cf93bb.wav", "transcript_path": "train_33/txt/004c58cf93bb.txt"}, {"wav_path": "train_33/wav/005365fc5413.wav", "transcript_path": "train_33/txt/005365fc5413.txt"}, {"wav_path": "train_33/wav/00575e9c0a42.wav", "transcript_path": "train_33/txt/00575e9c0a42.txt"}, {"wav_path": "train_33/wav/005cef06f0a1.wav", "transcript_path": "train_33/txt/005cef06f0a1.txt"}, {"wav_path": "train_33/wav/005eb106c67b.wav", "transcript_path": "train_33/txt/005eb106c67b.txt"}, {"wav_path": "train_33/wav/0066c805ae04.wav", "transcript_path": "train_33/txt/0066c805ae04.txt"}, {"wav_path": "train_33/wav/0068e93bf73d.wav", "transcript_path": "train_33/txt/0068e93bf73d.txt"}, {"wav_path": "train_33/wav/007398caa6aa.wav", "transcript_path": "train_33/txt/007398caa6aa.txt"}, {"wav_path": "train_33/wav/0077e67772f8.wav", "transcript_path": "train_33/txt/0077e67772f8.txt"}, {"wav_path": "train_33/wav/00990d6ba29f.wav", "transcript_path": "train_33/txt/00990d6ba29f.txt"}, {"wav_path": "train_33/wav/009c66814de5.wav", "transcript_path": "train_33/txt/009c66814de5.txt"}, {"wav_path": "train_33/wav/009f54505296.wav", "transcript_path": "train_33/txt/009f54505296.txt"}, {"wav_path": "train_33/wav/00a9acd617c7.wav", "transcript_path": "train_33/txt/00a9acd617c7.txt"}, {"wav_path": "train_33/wav/00b07e014880.wav", "transcript_path": "train_33/txt/00b07e014880.txt"}, {"wav_path": "train_33/wav/00bb68d09974.wav", "transcript_path": "train_33/txt/00bb68d09974.txt"}, {"wav_path": "train_33/wav/00beeeba5e64.wav", "transcript_path": "train_33/txt/00beeeba5e64.txt"}, {"wav_path": "train_33/wav/00c546fa3123.wav", "transcript_path": "train_33/txt/00c546fa3123.txt"}, {"wav_path": "train_33/wav/00c8441aa24b.wav", "transcript_path": "train_33/txt/00c8441aa24b.txt"}, {"wav_path": "train_33/wav/00cb5288a481.wav", "transcript_path": "train_33/txt/00cb5288a481.txt"}, {"wav_path": "train_33/wav/00ce5881e6db.wav", "transcript_path": "train_33/txt/00ce5881e6db.txt"}, {"wav_path": "train_33/wav/00d173531685.wav", "transcript_path": "train_33/txt/00d173531685.txt"}, {"wav_path": "train_33/wav/00da1f337c08.wav", "transcript_path": "train_33/txt/00da1f337c08.txt"}, {"wav_path": "train_33/wav/00e16634a592.wav", "transcript_path": "train_33/txt/00e16634a592.txt"}, {"wav_path": "train_33/wav/00f2608e5ef7.wav", "transcript_path": "train_33/txt/00f2608e5ef7.txt"}, {"wav_path": "train_33/wav/010a6866cf70.wav", "transcript_path": "train_33/txt/010a6866cf70.txt"}, {"wav_path": "train_33/wav/010fc6f2d7fa.wav", "transcript_path": "train_33/txt/010fc6f2d7fa.txt"}, {"wav_path": "train_33/wav/01144a2eb6b7.wav", "transcript_path": "train_33/txt/01144a2eb6b7.txt"}, {"wav_path": "train_33/wav/0116dd712748.wav", "transcript_path": "train_33/txt/0116dd712748.txt"}, {"wav_path": "train_33/wav/012cfd3b781a.wav", "transcript_path": "train_33/txt/012cfd3b781a.txt"}, {"wav_path": "train_33/wav/014d28a82dc4.wav", "transcript_path": "train_33/txt/014d28a82dc4.txt"}, {"wav_path": "train_33/wav/014d9b96eda3.wav", "transcript_path": "train_33/txt/014d9b96eda3.txt"}, {"wav_path": "train_33/wav/0153182cdc9d.wav", "transcript_path": "train_33/txt/0153182cdc9d.txt"}, {"wav_path": "train_33/wav/0155dc903a4e.wav", "transcript_path": "train_33/txt/0155dc903a4e.txt"}, {"wav_path": "train_33/wav/015ecde44824.wav", "transcript_path": "train_33/txt/015ecde44824.txt"}, {"wav_path": "train_33/wav/016415261f5b.wav", "transcript_path": "train_33/txt/016415261f5b.txt"}, {"wav_path": "train_33/wav/0169ef5e7655.wav", "transcript_path": "train_33/txt/0169ef5e7655.txt"}, {"wav_path": "train_33/wav/016a06ad0acf.wav", "transcript_path": "train_33/txt/016a06ad0acf.txt"}, {"wav_path": "train_33/wav/016c3ee53aba.wav", "transcript_path": "train_33/txt/016c3ee53aba.txt"}, {"wav_path": "train_33/wav/017a6eddbf80.wav", "transcript_path": "train_33/txt/017a6eddbf80.txt"}, {"wav_path": "train_33/wav/0185f16d89c4.wav", "transcript_path": "train_33/txt/0185f16d89c4.txt"}, {"wav_path": "train_33/wav/0187ba190716.wav", "transcript_path": "train_33/txt/0187ba190716.txt"}, {"wav_path": "train_33/wav/0190761d9de3.wav", "transcript_path": "train_33/txt/0190761d9de3.txt"}, {"wav_path": "train_33/wav/019ee422317e.wav", "transcript_path": "train_33/txt/019ee422317e.txt"}, {"wav_path": "train_33/wav/01a614d4a20a.wav", "transcript_path": "train_33/txt/01a614d4a20a.txt"}, {"wav_path": "train_33/wav/01aaed1fce8c.wav", "transcript_path": "train_33/txt/01aaed1fce8c.txt"}, {"wav_path": "train_33/wav/01b56c43b0fb.wav", "transcript_path": "train_33/txt/01b56c43b0fb.txt"}, {"wav_path": "train_33/wav/01ba699bb544.wav", "transcript_path": "train_33/txt/01ba699bb544.txt"}, {"wav_path": "train_33/wav/01c4418a371e.wav", "transcript_path": "train_33/txt/01c4418a371e.txt"}, {"wav_path": "train_33/wav/01c601924bf3.wav", "transcript_path": "train_33/txt/01c601924bf3.txt"}, {"wav_path": "train_33/wav/01db0ea2c8d5.wav", "transcript_path": "train_33/txt/01db0ea2c8d5.txt"}, {"wav_path": "train_33/wav/01e1b640ca06.wav", "transcript_path": "train_33/txt/01e1b640ca06.txt"}, {"wav_path": "train_33/wav/01e97502cbad.wav", "transcript_path": "train_33/txt/01e97502cbad.txt"}, {"wav_path": "train_33/wav/01f2b425e33f.wav", "transcript_path": "train_33/txt/01f2b425e33f.txt"}, {"wav_path": "train_33/wav/01f4dfaa7a1d.wav", "transcript_path": "train_33/txt/01f4dfaa7a1d.txt"}, {"wav_path": "train_33/wav/0202a2ef9ec7.wav", "transcript_path": "train_33/txt/0202a2ef9ec7.txt"}, {"wav_path": "train_33/wav/020b4079dfad.wav", "transcript_path": "train_33/txt/020b4079dfad.txt"}, {"wav_path": "train_33/wav/020cc0d264a4.wav", "transcript_path": "train_33/txt/020cc0d264a4.txt"}, {"wav_path": "train_33/wav/021f954b4feb.wav", "transcript_path": "train_33/txt/021f954b4feb.txt"}, {"wav_path": "train_33/wav/0225fda02e2b.wav", "transcript_path": "train_33/txt/0225fda02e2b.txt"}, {"wav_path": "train_33/wav/0227e86689ca.wav", "transcript_path": "train_33/txt/0227e86689ca.txt"}, {"wav_path": "train_33/wav/02481c74bb4d.wav", "transcript_path": "train_33/txt/02481c74bb4d.txt"}, {"wav_path": "train_33/wav/02492b9ad154.wav", "transcript_path": "train_33/txt/02492b9ad154.txt"}, {"wav_path": "train_33/wav/024eef819af2.wav", "transcript_path": "train_33/txt/024eef819af2.txt"}, {"wav_path": "train_33/wav/025234e4ae89.wav", "transcript_path": "train_33/txt/025234e4ae89.txt"}, {"wav_path": "train_33/wav/02570037eae7.wav", "transcript_path": "train_33/txt/02570037eae7.txt"}, {"wav_path": "train_33/wav/025ef9d79e59.wav", "transcript_path": "train_33/txt/025ef9d79e59.txt"}, {"wav_path": "train_33/wav/027cc3f8b418.wav", "transcript_path": "train_33/txt/027cc3f8b418.txt"}, {"wav_path": "train_33/wav/027ef6634bfb.wav", "transcript_path": "train_33/txt/027ef6634bfb.txt"}, {"wav_path": "train_33/wav/0289cff2ba11.wav", "transcript_path": "train_33/txt/0289cff2ba11.txt"}, {"wav_path": "train_33/wav/0296971cde4e.wav", "transcript_path": "train_33/txt/0296971cde4e.txt"}, {"wav_path": "train_33/wav/029ba9773949.wav", "transcript_path": "train_33/txt/029ba9773949.txt"}, {"wav_path": "train_33/wav/029bc7828db9.wav", "transcript_path": "train_33/txt/029bc7828db9.txt"}, {"wav_path": "train_33/wav/029f0b3b3cdf.wav", "transcript_path": "train_33/txt/029f0b3b3cdf.txt"}, {"wav_path": "train_33/wav/02a805aed26e.wav", "transcript_path": "train_33/txt/02a805aed26e.txt"}, {"wav_path": "train_33/wav/02b22d768d60.wav", "transcript_path": "train_33/txt/02b22d768d60.txt"}, {"wav_path": "train_33/wav/02c00639a052.wav", "transcript_path": "train_33/txt/02c00639a052.txt"}, {"wav_path": "train_33/wav/02c27bc8588e.wav", "transcript_path": "train_33/txt/02c27bc8588e.txt"}, {"wav_path": "train_33/wav/02c569b82528.wav", "transcript_path": "train_33/txt/02c569b82528.txt"}, {"wav_path": "train_33/wav/02c71cb3657d.wav", "transcript_path": "train_33/txt/02c71cb3657d.txt"}, {"wav_path": "train_33/wav/02cb76a4aa91.wav", "transcript_path": "train_33/txt/02cb76a4aa91.txt"}, {"wav_path": "train_33/wav/02d85e5c1fbd.wav", "transcript_path": "train_33/txt/02d85e5c1fbd.txt"}, {"wav_path": "train_33/wav/02db57a60a1d.wav", "transcript_path": "train_33/txt/02db57a60a1d.txt"}, {"wav_path": "train_33/wav/03010b2887d6.wav", "transcript_path": "train_33/txt/03010b2887d6.txt"}, {"wav_path": "train_33/wav/030347ef6679.wav", "transcript_path": "train_33/txt/030347ef6679.txt"}, {"wav_path": "train_33/wav/0315942a03a3.wav", "transcript_path": "train_33/txt/0315942a03a3.txt"}, {"wav_path": "train_33/wav/031774cc4853.wav", "transcript_path": "train_33/txt/031774cc4853.txt"}, {"wav_path": "train_33/wav/031fb3e9fcd8.wav", "transcript_path": "train_33/txt/031fb3e9fcd8.txt"}, {"wav_path": "train_33/wav/03215ec15451.wav", "transcript_path": "train_33/txt/03215ec15451.txt"}, {"wav_path": "train_33/wav/03289616a808.wav", "transcript_path": "train_33/txt/03289616a808.txt"}, {"wav_path": "train_33/wav/032fa6d44b8f.wav", "transcript_path": "train_33/txt/032fa6d44b8f.txt"}, {"wav_path": "train_33/wav/0331c2a862be.wav", "transcript_path": "train_33/txt/0331c2a862be.txt"}, {"wav_path": "train_33/wav/033eab3e8726.wav", "transcript_path": "train_33/txt/033eab3e8726.txt"}, {"wav_path": "train_33/wav/034ac3ce9ee6.wav", "transcript_path": "train_33/txt/034ac3ce9ee6.txt"}, {"wav_path": "train_33/wav/0370786a0c8f.wav", "transcript_path": "train_33/txt/0370786a0c8f.txt"}]}